README.md
setup.py
toeicbert/__init__.py
toeicbert/__main__.py
toeicbert/toeicbert.py
toeicbert.egg-info/PKG-INFO
toeicbert.egg-info/SOURCES.txt
toeicbert.egg-info/dependency_links.txt
toeicbert.egg-info/requires.txt
toeicbert.egg-info/top_level.txt