Metadata-Version: 2.1
Name: toeicbert
Version: 0.0.2
Summary: TOEIC blank problem solving using pytorch-pretrained-BERT model.
Home-page: https://github.com/graykode/toeicbert
Author: Tae Hwan Jung(@graykode)
Author-email: nlkey2022@gmail.com
License: MIT
Keywords: BERT TOEIC pytorch-pretrained-BERT bert nlp NLP
Platform: UNKNOWN
